MANIFEST.in
README.md
setup.cfg
setup.py
baseapp_auth/__init__.py
baseapp_auth/admin.py
baseapp_auth/apps.py
baseapp_auth/emails.py
baseapp_auth/exceptions.py
baseapp_auth/forms.py
baseapp_auth/managers.py
baseapp_auth/models.py
baseapp_auth/password_validators.py
baseapp_auth/permissions.py
baseapp_auth/pipeline.py
baseapp_auth/querysets.py
baseapp_auth/settings.py
baseapp_auth/tasks.py
baseapp_auth/tokens.py
baseapp_auth.egg-info/PKG-INFO
baseapp_auth.egg-info/SOURCES.txt
baseapp_auth.egg-info/dependency_links.txt
baseapp_auth.egg-info/requires.txt
baseapp_auth.egg-info/top_level.txt
baseapp_auth/graphql/__init__.py
baseapp_auth/graphql/filters.py
baseapp_auth/graphql/object_types.py
baseapp_auth/graphql/permissions.py
baseapp_auth/graphql/queries.py
baseapp_auth/locale/es/LC_MESSAGES/django.mo
baseapp_auth/locale/es/LC_MESSAGES/django.po
baseapp_auth/migrations/0001_initial.py
baseapp_auth/migrations/0002_passwordvalidation.py
baseapp_auth/migrations/0003_superuserupdatelog.py
baseapp_auth/migrations/0004_alter_superuserupdatelog_assigner.py
baseapp_auth/migrations/__init__.py
baseapp_auth/rest_framework/__init__.py
baseapp_auth/rest_framework/change_email/__init__.py
baseapp_auth/rest_framework/change_email/serializers.py
baseapp_auth/rest_framework/change_email/views.py
baseapp_auth/rest_framework/change_expired_password/__init__.py
baseapp_auth/rest_framework/change_expired_password/serializers.py
baseapp_auth/rest_framework/change_expired_password/views.py
baseapp_auth/rest_framework/confirm_email/__init__.py
baseapp_auth/rest_framework/confirm_email/serializers.py
baseapp_auth/rest_framework/confirm_email/views.py
baseapp_auth/rest_framework/forgot_password/__init__.py
baseapp_auth/rest_framework/forgot_password/serializers.py
baseapp_auth/rest_framework/forgot_password/views.py
baseapp_auth/rest_framework/jwt/__init__.py
baseapp_auth/rest_framework/jwt/serializers.py
baseapp_auth/rest_framework/jwt/tokens.py
baseapp_auth/rest_framework/jwt/views.py
baseapp_auth/rest_framework/login/__init__.py
baseapp_auth/rest_framework/login/helpers.py
baseapp_auth/rest_framework/login/serializers.py
baseapp_auth/rest_framework/login/views.py
