Metadata-Version: 2.1
Name: baseapp-auth
Version: 0.4.14
Summary: BaseApp Auth
Home-page: https://github.com/silverlogic/baseapp-backend
Author: The SilverLogic
Author-email: dev@tsl.io
License: BSD-3-Clause  # Example license
Platform: UNKNOWN
Requires-Python: >=3.8
